_appmap/__init__.py
_appmap/configuration.py
_appmap/django.py
_appmap/env.py
_appmap/event.py
_appmap/fastapi.py
_appmap/flask.py
_appmap/generation.py
_appmap/importer.py
_appmap/instrument.py
_appmap/labels.py
_appmap/metadata.py
_appmap/noappmap.py
_appmap/py_version_check.py
_appmap/recorder.py
_appmap/recording.py
_appmap/remote_recording.py
_appmap/singleton.py
_appmap/testing_framework.py
_appmap/trace_logger.py
_appmap/unittest.py
_appmap/utils.py
_appmap/web_framework.py
appmap/__init__.py
appmap/command/__init__.py
appmap/command/appmap_agent_init.py
appmap/command/appmap_agent_status.py
appmap/command/appmap_agent_validate.py
appmap/command/runner.py
appmap/django.py
appmap/fastapi.py
appmap/flask.py
appmap/http.py
appmap/labeling/__init__.py
appmap/labeling/crypto.yml
appmap/labeling/django.yml
appmap/labeling/flask.yml
appmap/labeling/formats.yml
appmap/labeling/http.yml
appmap/labeling/jobs.yml
appmap/labeling/jwt.yml
appmap/labeling/logger.yml
appmap/labeling/random.yml
appmap/pytest.py
appmap/sqlalchemy.py
appmap/unittest.py
appmap/uvicorn.py
appmap.pth
_appmap/wrapt/LICENSE
_appmap/wrapt/__init__.py
_appmap/wrapt/arguments.py
_appmap/wrapt/decorators.py
_appmap/wrapt/importer.py
_appmap/wrapt/wrappers.py
appmap-2.1.8.dist-info/LICENSE
appmap-2.1.8.dist-info/METADATA
appmap-2.1.8.dist-info/WHEEL
appmap-2.1.8.dist-info/entry_points.txt
appmap-2.1.8.dist-info/RECORD
