Metadata-Version: 2.1
Name: appmap
Version: 2.1.8
Summary: Create AppMap files by recording a Python application.
Home-page: https://github.com/applandinc/appmap-python
License: MIT
Author: Alan Potter
Author-email: alan@app.land
Requires-Python: >=3.8,<4.0
Classifier: Development Status :: 4 - Beta
Classifier: Framework :: Django
Classifier: Framework :: Django :: 3.2
Classifier: Framework :: Flask
Classifier: Framework :: Pytest
Classifier: Intended Audience :: Developers
Classifier: License :: OSI Approved :: MIT License
Classifier: Programming Language :: Python :: 3
Classifier: Programming Language :: Python :: 3.8
Classifier: Programming Language :: Python :: 3.9
Classifier: Programming Language :: Python :: 3.10
Classifier: Programming Language :: Python :: 3.11
Classifier: Programming Language :: Python :: 3.12
Classifier: Programming Language :: Python :: 3.13
Classifier: Topic :: Software Development
Classifier: Topic :: Software Development :: Debuggers
Classifier: Topic :: Software Development :: Documentation
Requires-Dist: PyYAML (>=5.3.0)
Requires-Dist: importlib-resources (>=5.4.0,<6.0.0)
Requires-Dist: inflection (>=0.3.0)
Requires-Dist: packaging (>=19.0)
